plz/__init__.py
plz/plz_cli.py
tests/__init__.py
tests/conftest.py
tests/test_init.py
tests/test_install.py
tests/test_lock.py
tests/utils.py
plz-0.2.1.dist-info/LICENSE
plz-0.2.1.dist-info/METADATA
plz-0.2.1.dist-info/WHEEL
plz-0.2.1.dist-info/entry_points.txt
plz-0.2.1.dist-info/top_level.txt
plz-0.2.1.dist-info/RECORD
