Metadata-Version: 2.1
Name: plz
Version: 0.2.1
Summary: plz is lightweight and simple virtual environment and dependencies manager, wrapping virtualenv and piptools together
Home-page: https://github.com/royreznik/plz
Author: Roy Reznik
Author-email: royreznik@gmail.com
License: MIT License
Classifier: Development Status :: 5 - Production/Stable
Classifier: Intended Audience :: Developers
Classifier: Intended Audience :: System Administrators
Classifier: License :: OSI Approved :: MIT License
Classifier: Natural Language :: English
Classifier: Operating System :: OS Independent
Classifier: Programming Language :: Python
Classifier: Programming Language :: Python :: 3
Classifier: Programming Language :: Python :: 3.8
Classifier: Programming Language :: Python :: 3.9
Classifier: Programming Language :: Python :: 3.10
Classifier: Programming Language :: Python :: 3.11
Classifier: Programming Language :: Python :: 3 :: Only
Classifier: Programming Language :: Python :: Implementation :: CPython
Classifier: Topic :: Software Development :: Libraries
Classifier: Topic :: System :: Systems Administration
Classifier: Typing :: Typed
Requires-Python: >=3.8, <4
License-File: LICENSE
Requires-Dist: pip-tools
Requires-Dist: virtualenv
Requires-Dist: click
